LICENSE
MANIFEST.in
README.rst
setup.cfg
setup.py
pglifecycle/__init__.py
pglifecycle/clean_role_acls.py
pglifecycle/cli.py
pglifecycle/common.py
pglifecycle/constants.py
pglifecycle/generate_dump.py
pglifecycle/generate_project.py
pglifecycle/parse.py
pglifecycle/pgdump.py
pglifecycle/storage.py
pglifecycle/utils.py
pglifecycle.egg-info/PKG-INFO
pglifecycle.egg-info/SOURCES.txt
pglifecycle.egg-info/dependency_links.txt
pglifecycle.egg-info/entry_points.txt
pglifecycle.egg-info/requires.txt
pglifecycle.egg-info/top_level.txt
pglifecycle.egg-info/zip-safe