Metadata-Version: 2.1
Name: pglifecycle
Version: 1.0.0a3
Summary: A PostgreSQL schema management tool
Home-page: https://github.com/gmr/pglifecycle
Author: Gavin M. Roy
Author-email: gavinmroy@gmail.com
License: BSD 3-Clause License
Project-URL: Bug Tracker, https://github.com/gmr/pglifecycle/issues
Project-URL: Documentation, https://pglifecycle.readthedocs.io
Project-URL: Source Code, https://github.com/gmr/pglifecycle/
Keywords: postgresql,ddl,sql,schema
Platform: UNKNOWN
Classifier: Development Status :: 3 - Alpha
Classifier: Intended Audience :: Developers
Classifier: Intended Audience :: System Administrators
Classifier: License :: OSI Approved :: BSD License
Classifier: Natural Language :: English
Classifier: Operating System :: OS Independent
Classifier: Programming Language :: Python :: 3
Classifier: Programming Language :: Python :: 3.7
Classifier: Programming Language :: Python :: 3.8
Classifier: Programming Language :: Python :: 3 :: Only
Classifier: Programming Language :: Python :: Implementation :: CPython
Classifier: Programming Language :: SQL
Classifier: Topic :: Database
Classifier: Topic :: System :: Systems Administration
Classifier: Topic :: Software Development
